Workbook

Sheet Summary
A1: Test case summary: QA Orders platform
A2: Legend: blue cells on 'Test Cases' (Status, Notes) are for you to edit; everything on this sheet is a formula and updates automatically. Example: set TC-AUTH-001 to Pass and watch 'Pass rate' change.
A4: Headline metric | B4: Value
A5: Total test cases | B5: =COUNTA('Test Cases'!$A$2:$A$1000) -> 129
A6: Fully automated | B6: =COUNTIF('Test Cases'!$K$2:$K$1000,"Automated") -> 98
A7: Partly automated | B7: =COUNTIF('Test Cases'!$K$2:$K$1000,"Partial") -> 4
A8: Manual only | B8: =COUNTIF('Test Cases'!$K$2:$K$1000,"Manual") -> 27
A9: Automated or partial (%) | B9: =IFERROR((B6+B7)/B5,0) -> 0.79069767
A10: Requirements covered (%) | B10: =IFERROR(COUNTIF(Requirements!$D$2:$D$21,"Yes")/COUNTA(Requirements!$A$2:$A$21),0) -> 1
A11: Seeded bugs with at least one linked case | B11: =COUNTIF('Seeded Bugs'!$E$2:$E$16,">0") -> 15
A12: Executed (Pass + Fail + Blocked) | B12: =COUNTIF('Test Cases'!$M$2:$M$1000,"Pass")+COUNTIF('Test Cases'!$M$2:$M$1000,"Fail")+COUNTIF('Test Cases'!$M$2:$M$1000,"Blocked") -> 0
A13: Pass rate of executed | B13: =IFERROR(COUNTIF('Test Cases'!$M$2:$M$1000,"Pass")/B12,0) -> 0
A15: By test type | B15: Count | C15: Share
A16: API | B16: =COUNTIF('Test Cases'!$E$2:$E$1000,A16) -> 47 | C16: =IFERROR(B16/$B$5,0) -> 0.36434109
A17: Functional | B17: =COUNTIF('Test Cases'!$E$2:$E$1000,A17) -> 14 | C17: =IFERROR(B17/$B$5,0) -> 0.10852713
A18: Integration | B18: =COUNTIF('Test Cases'!$E$2:$E$1000,A18) -> 15 | C18: =IFERROR(B18/$B$5,0) -> 0.11627907
A19: Regression | B19: =COUNTIF('Test Cases'!$E$2:$E$1000,A19) -> 4 | C19: =IFERROR(B19/$B$5,0) -> 0.031007752
A20: Compatibility | B20: =COUNTIF('Test Cases'!$E$2:$E$1000,A20) -> 13 | C20: =IFERROR(B20/$B$5,0) -> 0.10077519
A21: Security | B21: =COUNTIF('Test Cases'!$E$2:$E$1000,A21) -> 16 | C21: =IFERROR(B21/$B$5,0) -> 0.12403101
A22: Accessibility | B22: =COUNTIF('Test Cases'!$E$2:$E$1000,A22) -> 11 | C22: =IFERROR(B22/$B$5,0) -> 0.085271318
A23: Database | B23: =COUNTIF('Test Cases'!$E$2:$E$1000,A23) -> 9 | C23: =IFERROR(B23/$B$5,0) -> 0.069767442
A25: By layer | B25: Count | C25: Share
A26: API | B26: =COUNTIF('Test Cases'!$F$2:$F$1000,A26) -> 82 | C26: =IFERROR(B26/$B$5,0) -> 0.63565891
A27: UI | B27: =COUNTIF('Test Cases'!$F$2:$F$1000,A27) -> 38 | C27: =IFERROR(B27/$B$5,0) -> 0.29457364
A28: DB | B28: =COUNTIF('Test Cases'!$F$2:$F$1000,A28) -> 9 | C28: =IFERROR(B28/$B$5,0) -> 0.069767442
A30: By priority | B30: Count | C30: Share
A31: P1 | B31: =COUNTIF('Test Cases'!$G$2:$G$1000,A31) -> 38 | C31: =IFERROR(B31/$B$5,0) -> 0.29457364
A32: P2 | B32: =COUNTIF('Test Cases'!$G$2:$G$1000,A32) -> 56 | C32: =IFERROR(B32/$B$5,0) -> 0.43410853
A33: P3 | B33: =COUNTIF('Test Cases'!$G$2:$G$1000,A33) -> 32 | C33: =IFERROR(B33/$B$5,0) -> 0.24806202
A34: P4 | B34: =COUNTIF('Test Cases'!$G$2:$G$1000,A34) -> 3 | C34: =IFERROR(B34/$B$5,0) -> 0.023255814
A36: By module | B36: Count | C36: Share
A37: AUTH | B37: =COUNTIF('Test Cases'!$B$2:$B$1000,A37) -> 23 | C37: =IFERROR(B37/$B$5,0) -> 0.17829457
A38: ORD | B38: =COUNTIF('Test Cases'!$B$2:$B$1000,A38) -> 37 | C38: =IFERROR(B38/$B$5,0) -> 0.28682171
A39: LIST | B39: =COUNTIF('Test Cases'!$B$2:$B$1000,A39) -> 11 | C39: =IFERROR(B39/$B$5,0) -> 0.085271318
A40: FLOW | B40: =COUNTIF('Test Cases'!$B$2:$B$1000,A40) -> 15 | C40: =IFERROR(B40/$B$5,0) -> 0.11627907
A41: STAT | B41: =COUNTIF('Test Cases'!$B$2:$B$1000,A41) -> 5 | C41: =IFERROR(B41/$B$5,0) -> 0.03875969
A42: A11Y | B42: =COUNTIF('Test Cases'!$B$2:$B$1000,A42) -> 11 | C42: =IFERROR(B42/$B$5,0) -> 0.085271318
A43: COMP | B43: =COUNTIF('Test Cases'!$B$2:$B$1000,A43) -> 15 | C43: =IFERROR(B43/$B$5,0) -> 0.11627907
A44: DB | B44: =COUNTIF('Test Cases'!$B$2:$B$1000,A44) -> 9 | C44: =IFERROR(B44/$B$5,0) -> 0.069767442
A45: CLOUD | B45: =COUNTIF('Test Cases'!$B$2:$B$1000,A45) -> 3 | C45: =IFERROR(B45/$B$5,0) -> 0.023255814
A47: By status | B47: Count | C47: Share
A48: Not Run | B48: =COUNTIF('Test Cases'!$M$2:$M$1000,A48) -> 129 | C48: =IFERROR(B48/$B$5,0) -> 1
A49: Pass | B49: =COUNTIF('Test Cases'!$M$2:$M$1000,A49) -> 0 | C49: =IFERROR(B49/$B$5,0) -> 0
A50: Fail | B50: =COUNTIF('Test Cases'!$M$2:$M$1000,A50) -> 0 | C50: =IFERROR(B50/$B$5,0) -> 0
A51: Blocked | B51: =COUNTIF('Test Cases'!$M$2:$M$1000,A51) -> 0 | C51: =IFERROR(B51/$B$5,0) -> 0
A53: Note: 'Share' columns are relative to the total number of test cases.

Sheet Test Cases
A1: ID | B1: Module | C1: Req ID | D1: Title | E1: Type | F1: Layer | G1: Priority | H1: Steps | I1: Expected result | J1: Automated in | K1: Automation | L1: Seeded bug | M1: Status | N1: Notes
A2: TC-AUTH-001 | B2: AUTH | C2: R-01 | D2: Register a valid user | E2: API | F2: API | G2: P1 | H2: POST /register with valid name, e-mail, password | I2: 201; token and user returned | J2: Postman; REST Assured | K2: Automated | M2: Not Run
A3: TC-AUTH-002 | B3: AUTH | C3: R-01 | D3: Password hash is never returned | E3: Security | F3: API | G3: P2 | H3: Register; inspect the JSON body | I3: No 'password' field anywhere in the response | J3: Postman; REST Assured | K3: Automated | M3: Not Run
A4: TC-AUTH-003 | B4: AUTH | C4: R-01 | D4: Duplicate e-mail rejected | E4: API | F4: API | G4: P2 | H4: Register the same e-mail twice | I4: Second call 422 with an e-mail error | J4: Postman; REST Assured | K4: Automated | M4: Not Run
A5: TC-AUTH-004 | B5: AUTH | C5: R-01 | D5: Malformed e-mail rejected | E5: API | F5: API | G5: P2 | H5: Register with a unique per-run value such as 'plainaddress<token>', '@no-local-<token>.com', 'two<token>@@x.com', 'a b<token>@c.com' | I5: 422 for each value | J5: Postman; REST Assured; Cypress | K5: Automated | L5: BUG-001 | M5: Not Run
A6: TC-AUTH-005 | B6: AUTH | C6: R-01 | D6: Missing fields rejected | E6: API | F6: API | G6: P2 | H6: POST /register with {} | I6: 422 listing name, email and password errors | J6: Postman | K6: Automated | M6: Not Run
A7: TC-AUTH-006 | B7: AUTH | C7: R-01 | D7: Plus-addressed e-mail accepted | E7: Functional | F7: API | G7: P3 | H7: Register 'user+tag@example.com' | I7: 201 | J7: Manual | K7: Manual | M7: Not Run
A8: TC-AUTH-007 | B8: AUTH | C8: R-02 | D8: Password length 7 rejected | E8: API | F8: API | G8: P2 | H8: Register with a 7-character password | I8: 422 | J8: Postman; REST Assured | K8: Automated | M8: Not Run
A9: TC-AUTH-008 | B9: AUTH | C9: R-02 | D9: Password length 8 accepted | E9: API | F9: API | G9: P2 | H9: Register with an 8-character password | I9: 201 | J9: Postman; REST Assured | K9: Automated | M9: Not Run
A10: TC-AUTH-009 | B10: AUTH | C10: R-02 | D10: Password length 72 accepted, 73 rejected | E10: API | F10: API | G10: P3 | H10: Register with 72 then 73 characters | I10: 201 then 422 | J10: Manual | K10: Manual | M10: Not Run
A11: TC-AUTH-010 | B11: AUTH | C11: R-02 | D11: Name length 100 accepted, 101 rejected | E11: API | F11: API | G11: P3 | H11: Register with a 100 then 101 character name | I11: 201 then 422 | J11: Manual | K11: Manual | M11: Not Run
A12: TC-AUTH-011 | B12: AUTH | C12: R-03 | D12: Login with valid credentials | E12: API | F12: API | G12: P1 | H12: POST /login with a registered user | I12: 200 and a token | J12: Postman; REST Assured | K12: Automated | M12: Not Run
A13: TC-AUTH-012 | B13: AUTH | C13: R-03 | D13: Login with wrong password | E13: API | F13: API | G13: P1 | H13: POST /login with a wrong password | I13: 401 'Invalid credentials' | J13: Postman | K13: Automated | M13: Not Run
A14: TC-AUTH-013 | B14: AUTH | C14: R-03 | D14: Unknown e-mail is indistinguishable from wrong password | E14: Security | F14: API | G14: P2 | H14: Login with an unregistered e-mail | I14: 401 with the same message as a wrong password | J14: Postman; REST Assured; Cypress | K14: Automated | L14: BUG-008 | M14: Not Run
A15: TC-AUTH-014 | B15: AUTH | C15: R-03 | D15: Login with empty body | E15: API | F15: API | G15: P3 | H15: POST /login with {} | I15: 422 | J15: Postman | K15: Automated | M15: Not Run
A16: TC-AUTH-015 | B16: AUTH | C16: R-03 | D16: SQL injection string in login | E16: Security | F16: API | G16: P2 | H16: Login with e-mail "' OR '1'='1" | I16: No 5xx, no token issued | J16: Postman | K16: Automated | M16: Not Run
A17: TC-AUTH-016 | B17: AUTH | C17: R-03 | D17: Failed login is visible in the UI | E17: Functional | F17: UI | G17: P2 | H17: Submit the login form with wrong credentials | I17: A role=alert error message is displayed | J17: Cypress; Playwright | K17: Automated | L17: BUG-015 | M17: Not Run
A18: TC-AUTH-017 | B18: AUTH | C18: R-04 | D18: GET /me with a valid token | E18: API | F18: API | G18: P1 | H18: Call /me with a Bearer token | I18: 200 and the user's profile | J18: Postman; REST Assured | K18: Automated | M18: Not Run
A19: TC-AUTH-018 | B19: AUTH | C19: R-04 | D19: GET /me without token | E19: Security | F19: API | G19: P1 | H19: Call /me with no Authorization header | I19: 401 | J19: Postman; REST Assured | K19: Automated | M19: Not Run
A20: TC-AUTH-019 | B20: AUTH | C20: R-04 | D20: GET /me with a garbage token | E20: Security | F20: API | G20: P2 | H20: Authorization: Bearer garbage | I20: 401 | J20: Postman; REST Assured | K20: Automated | M20: Not Run
A21: TC-AUTH-020 | B21: AUTH | C21: R-04 | D21: Logout revokes the token | E21: Integration | F21: API | G21: P1 | H21: Logout, then call /me with the same token | I21: Logout 200, then 401 | J21: Postman; REST Assured | K21: Automated | M21: Not Run
A22: TC-AUTH-021 | B22: AUTH | C22: R-04 | D22: Logging out one session keeps another valid | E22: Integration | F22: API | G22: P3 | H22: Login twice (tokens T1, T2); logout T1; call /me with T2 | I22: T2 still returns 200 | J22: Manual | K22: Manual | M22: Not Run
A23: TC-AUTH-022 | B23: AUTH | C23: R-04 | D23: UI registration lands on the orders list | E23: Functional | F23: UI | G23: P1 | H23: Register through the form | I23: Orders page is shown | J23: Cypress | K23: Automated | M23: Not Run
A24: TC-AUTH-023 | B24: AUTH | C24: R-04 | D24: UI login and logout | E24: Functional | F24: UI | G24: P1 | H24: Login, then press Log out | I24: Orders page, then the login form again | J24: Cypress | K24: Automated | M24: Not Run
A25: TC-ORD-001 | B25: ORD | C25: R-05 | D25: Create a single-item order | E25: API | F25: API | G25: P1 | H25: POST /orders with one item | I25: 201; status 'created'; item persisted | J25: Postman; REST Assured | K25: Automated | M25: Not Run
A26: TC-ORD-002 | B26: ORD | C26: R-07 | D26: Total is the sum of qty x price for several items | E26: API | F26: API | G26: P1 | H26: Create an order with 3x9.99 and 1x0.01 | I26: total 29.98 | J26: Postman; REST Assured | K26: Automated | M26: Not Run
A27: TC-ORD-003 | B27: ORD | C27: R-07 | D27: Smallest price and quantity rounding | E27: API | F27: API | G27: P3 | H27: 3 x 0.01 | I27: total 0.03 | J27: Manual | K27: Manual | M27: Not Run
A28: TC-ORD-004 | B28: ORD | C28: R-07 | D28: No hidden discount on bulk quantities | E28: API | F28: API | G28: P1 | H28: Create an order with qty 10 x 100 | I28: total 1000.00 | J28: Postman; REST Assured; Cypress; PL/SQL | K28: Automated | L28: BUG-007 | M28: Not Run
A29: TC-ORD-005 | B29: ORD | C29: R-06 | D29: Quantity 0 rejected | E29: API | F29: API | G29: P1 | H29: POST an item with quantity 0 | I29: 422 | J29: Postman; REST Assured; Cypress; PL/SQL | K29: Automated | L29: BUG-002 | M29: Not Run
A30: TC-ORD-006 | B30: ORD | C30: R-06 | D30: Negative quantity rejected | E30: API | F30: API | G30: P1 | H30: POST an item with quantity -5 | I30: 422 | J30: Postman; REST Assured; PL/SQL | K30: Automated | L30: BUG-002 | M30: Not Run
A31: TC-ORD-007 | B31: ORD | C31: R-06 | D31: Quantity 1 accepted (lower boundary) | E31: API | F31: API | G31: P2 | H31: POST an item with quantity 1 | I31: 201 | J31: REST Assured | K31: Automated | M31: Not Run
A32: TC-ORD-008 | B32: ORD | C32: R-06 | D32: Quantity 1000 accepted (upper boundary) | E32: API | F32: API | G32: P2 | H32: POST an item with quantity 1000 | I32: 201 | J32: Postman; REST Assured | K32: Automated | M32: Not Run
A33: TC-ORD-009 | B33: ORD | C33: R-06 | D33: Quantity 1001 rejected | E33: API | F33: API | G33: P2 | H33: POST an item with quantity 1001 | I33: 422 | J33: Postman; REST Assured | K33: Automated | L33: BUG-002 | M33: Not Run
A34: TC-ORD-010 | B34: ORD | C34: R-06 | D34: Fractional quantity rejected | E34: API | F34: API | G34: P3 | H34: POST an item with quantity 1.5 | I34: 422 | J34: Manual | K34: Manual | M34: Not Run
A35: TC-ORD-011 | B35: ORD | C35: R-06 | D35: Non-numeric quantity rejected | E35: API | F35: API | G35: P3 | H35: POST an item with quantity 'abc' | I35: 422 | J35: Postman | K35: Automated | M35: Not Run
A36: TC-ORD-012 | B36: ORD | C36: R-06 | D36: Unit price 0 rejected | E36: API | F36: API | G36: P2 | H36: POST an item with unit_price 0 | I36: 422 | J36: Postman | K36: Automated | M36: Not Run
A37: TC-ORD-013 | B37: ORD | C37: R-06 | D37: Unit price 0.01 accepted | E37: API | F37: API | G37: P3 | H37: POST an item with unit_price 0.01 | I37: 201 | J37: Postman | K37: Automated | M37: Not Run
A38: TC-ORD-014 | B38: ORD | C38: R-06 | D38: Unit price 100000 accepted, 100000.01 rejected | E38: API | F38: API | G38: P3 | H38: POST both values | I38: 201 then 422 | J38: Manual | K38: Manual | M38: Not Run
A39: TC-ORD-015 | B39: ORD | C39: R-06 | D39: customer_name missing | E39: API | F39: API | G39: P2 | H39: POST without customer_name | I39: 422 | J39: Postman | K39: Automated | M39: Not Run
A40: TC-ORD-016 | B40: ORD | C40: R-06 | D40: customer_name 100 accepted, 101 rejected with 422 (not 500) | E40: API | F40: API | G40: P2 | H40: POST 100 then 101 characters | I40: 201 then 422 | J40: Postman; REST Assured; Cypress | K40: Automated | L40: BUG-009 | M40: Not Run
A41: TC-ORD-017 | B41: ORD | C41: R-06 | D41: Empty items list rejected | E41: API | F41: API | G41: P2 | H41: POST items: [] | I41: 422 | J41: Postman | K41: Automated | M41: Not Run
A42: TC-ORD-018 | B42: ORD | C42: R-06 | D42: 20 items accepted, 21 rejected | E42: API | F42: API | G42: P3 | H42: POST 20 then 21 items | I42: 201 then 422 | J42: Postman | K42: Automated | M42: Not Run
A43: TC-ORD-019 | B43: ORD | C43: R-06 | D43: SKU 32 chars accepted, 33 rejected | E43: API | F43: API | G43: P3 | H43: POST both lengths | I43: 201 then 422 | J43: Manual | K43: Manual | M43: Not Run
A44: TC-ORD-020 | B44: ORD | C44: R-05 | D44: Create without a token | E44: Security | F44: API | G44: P1 | H44: POST /orders without Authorization | I44: 401 | J44: Postman | K44: Automated | M44: Not Run
A45: TC-ORD-021 | B45: ORD | C45: R-05 | D45: Script tag in customer_name is stored as text | E45: Security | F45: API | G45: P2 | H45: POST customer_name '<script>alert(1)</script>' | I45: Response is application/json; UI renders it as text, no script runs | J45: Postman; Manual | K45: Partial | M45: Not Run
A46: TC-ORD-022 | B46: ORD | C46: R-05 | D46: Unicode customer_name round-trips | E46: Functional | F46: API | G46: P3 | H46: POST 'Zoe 株式会社' and GET it back | I46: Identical value returned | J46: Manual | K46: Manual | M46: Not Run
A47: TC-ORD-023 | B47: ORD | C47: R-05 | D47: UI shows the correct total after creating an order | E47: Functional | F47: UI | G47: P1 | H47: Create 3 x 19.99 in the form | I47: Detail page shows $59.97 and status 'created' | J47: Cypress | K47: Automated | M47: Not Run
A48: TC-ORD-024 | B48: ORD | C48: R-06 | D48: UI shows server validation errors | E48: Functional | F48: UI | G48: P2 | H48: Submit quantity 0 / a 101-char name | I48: Error list is displayed, no crash | J48: Cypress | K48: Automated | L48: BUG-002 | M48: Not Run
A49: TC-ORD-025 | B49: ORD | C49: R-05 | D49: UI: add and remove item lines | E49: Functional | F49: UI | G49: P3 | H49: Add two lines, remove one, submit | I49: Order contains the remaining line | J49: Manual | K49: Manual | M49: Not Run
A50: TC-ORD-026 | B50: ORD | C50: R-08 | D50: Read own order | E50: API | F50: API | G50: P1 | H50: GET /orders/{id} | I50: 200 with the order | J50: Postman; REST Assured | K50: Automated | M50: Not Run
A51: TC-ORD-027 | B51: ORD | C51: R-08 | D51: Unknown order id | E51: API | F51: API | G51: P2 | H51: GET /orders/99999999 | I51: 404 | J51: Postman; REST Assured | K51: Automated | M51: Not Run
A52: TC-ORD-028 | B52: ORD | C52: R-08 | D52: Non-numeric order id | E52: API | F52: API | G52: P3 | H52: GET /orders/abc | I52: 404 | J52: Postman | K52: Automated | M52: Not Run
A53: TC-ORD-029 | B53: ORD | C53: R-15 | D53: Cannot read another user's order | E53: Security | F53: API | G53: P1 | H53: User B GETs user A's order | I53: 403 | J53: Postman; REST Assured | K53: Automated | L53: BUG-003 | M53: Not Run
A54: TC-ORD-030 | B54: ORD | C54: R-10 | D54: Edit the customer name of a created order | E54: API | F54: API | G54: P2 | H54: PUT /orders/{id} | I54: 200 with the new name | J54: Postman | K54: Automated | M54: Not Run
A55: TC-ORD-031 | B55: ORD | C55: R-15 | D55: Cannot edit another user's order | E55: Security | F55: API | G55: P1 | H55: User B PUTs user A's order | I55: 403 | J55: Postman; REST Assured | K55: Automated | L55: BUG-003 | M55: Not Run
A56: TC-ORD-032 | B56: ORD | C56: R-10 | D56: Empty customer name rejected on edit | E56: API | F56: API | G56: P3 | H56: PUT with an empty name | I56: 422 | J56: Manual | K56: Manual | M56: Not Run
A57: TC-ORD-033 | B57: ORD | C57: R-10 | D57: Paid order cannot be edited | E57: Integration | F57: API | G57: P2 | H57: Pay, then PUT | I57: 409 | J57: Postman; REST Assured | K57: Automated | M57: Not Run
A58: TC-ORD-034 | B58: ORD | C58: R-11 | D58: Delete a created order | E58: API | F58: API | G58: P2 | H58: DELETE /orders/{id} | I58: 204 | J58: Postman; REST Assured | K58: Automated | M58: Not Run
A59: TC-ORD-035 | B59: ORD | C59: R-11 | D59: Deleted order returns 404 | E59: Regression | F59: API | G59: P2 | H59: DELETE then GET | I59: 404 | J59: Postman; REST Assured | K59: Automated | M59: Not Run
A60: TC-ORD-036 | B60: ORD | C60: R-11 | D60: Paid order cannot be deleted | E60: Integration | F60: API | G60: P2 | H60: Pay, then DELETE | I60: 409 | J60: Postman; REST Assured | K60: Automated | M60: Not Run
A61: TC-ORD-037 | B61: ORD | C61: R-15 | D61: Cannot delete another user's order | E61: Security | F61: API | G61: P1 | H61: User B DELETEs user A's order | I61: 403 | J61: Manual | K61: Manual | L61: BUG-003 | M61: Not Run
A62: TC-LIST-001 | B62: LIST | C62: R-09 | D62: Default pagination metadata | E62: API | F62: API | G62: P2 | H62: GET /orders | I62: data array and meta page/per_page/total/last_page | J62: Postman | K62: Automated | M62: Not Run
A63: TC-LIST-002 | B63: LIST | C63: R-09 | D63: Pages never overlap | E63: Regression | F63: API | G63: P1 | H63: Create 5 orders; read pages 1-3 with per_page=2 | I63: 5 distinct ids across the pages | J63: Postman; REST Assured; Cypress | K63: Automated | L63: BUG-006 | M63: Not Run
A64: TC-LIST-003 | B64: LIST | C64: R-09 | D64: Last page may be partial | E64: API | F64: API | G64: P3 | H64: 3 orders, per_page=2 | I64: last_page 2; page 2 has 1 row | J64: REST Assured | K64: Automated | M64: Not Run
A65: TC-LIST-004 | B65: LIST | C65: R-09 | D65: Page beyond the last returns empty data | E65: API | F65: API | G65: P3 | H65: GET page=99 | I65: 200 with data: [] | J65: Manual | K65: Manual | M65: Not Run
A66: TC-LIST-005 | B66: LIST | C66: R-09 | D66: per_page is capped at 100 | E66: API | F66: API | G66: P3 | H66: GET per_page=5000 | I66: meta.per_page = 100 | J66: Postman | K66: Automated | M66: Not Run
A67: TC-LIST-006 | B67: LIST | C67: R-09 | D67: per_page=0 is clamped to 1 | E67: API | F67: API | G67: P4 | H67: GET per_page=0 | I67: meta.per_page = 1 | J67: Manual | K67: Manual | M67: Not Run
A68: TC-LIST-007 | B68: LIST | C68: R-09 | D68: Filter by status | E68: API | F68: API | G68: P3 | H68: GET ?status=paid | I68: Only paid orders | J68: Manual | K68: Manual | M68: Not Run
A69: TC-LIST-008 | B69: LIST | C69: R-09 | D69: Newest order first | E69: API | F69: API | G69: P4 | H69: Create two orders; list | I69: Higher id first | J69: Manual | K69: Manual | M69: Not Run
A70: TC-LIST-009 | B70: LIST | C70: R-15 | D70: User only sees their own orders | E70: Security | F70: API | G70: P1 | H70: User B lists orders | I70: meta.total = 0 | J70: Postman | K70: Automated | M70: Not Run
A71: TC-LIST-010 | B71: LIST | C71: R-09 | D71: UI empty state | E71: Functional | F71: UI | G71: P3 | H71: Open the orders list for a new user | I71: 'No orders yet.' is shown | J71: Cypress | K71: Automated | M71: Not Run
A72: TC-LIST-011 | B72: LIST | C72: R-09 | D72: UI pagination with 12 orders | E72: Functional | F72: UI | G72: P2 | H72: Open page 1, press Next | I72: 10 rows, then page 2 without repeated ids | J72: Cypress | K72: Automated | L72: BUG-006 | M72: Not Run
A73: TC-FLOW-001 | B73: FLOW | C73: R-12 | D73: Happy path: create, pay, ship | E73: Integration | F73: API | G73: P1 | H73: Create, POST /pay, POST /ship | I73: 200, 200; statuses paid then shipped | J73: Postman; REST Assured | K73: Automated | M73: Not Run
A74: TC-FLOW-002 | B74: FLOW | C74: R-12 | D74: Pay records a timestamp and one attempt | E74: Integration | F74: API | G74: P2 | H74: Pay an order | I74: paid_at set; payment_attempts = 1 | J74: Postman; REST Assured; PL/SQL | K74: Automated | M74: Not Run
A75: TC-FLOW-003 | B75: FLOW | C75: R-13 | D75: Cannot ship before paying | E75: Integration | F75: API | G75: P1 | H75: Ship a 'created' order | I75: 409 | J75: Postman; REST Assured; PL/SQL | K75: Automated | L75: BUG-005 | M75: Not Run
A76: TC-FLOW-004 | B76: FLOW | C76: R-12 | D76: Cannot pay twice | E76: Integration | F76: API | G76: P1 | H76: Pay the same order twice | I76: Second call 409; payment_attempts stays 1 | J76: Postman; REST Assured; PL/SQL | K76: Automated | L76: BUG-004 | M76: Not Run
A77: TC-FLOW-005 | B77: FLOW | C77: R-14 | D77: Cancel a created order | E77: Integration | F77: API | G77: P2 | H77: POST /cancel on a created order | I77: 200; status cancelled | J77: Postman | K77: Automated | M77: Not Run
A78: TC-FLOW-006 | B78: FLOW | C78: R-14 | D78: Cancel a paid order | E78: Integration | F78: API | G78: P2 | H78: Pay, then cancel | I78: 200; status cancelled | J78: Manual | K78: Manual | M78: Not Run
A79: TC-FLOW-007 | B79: FLOW | C79: R-14 | D79: Cannot cancel a shipped order | E79: Integration | F79: API | G79: P1 | H79: Pay, ship, cancel | I79: 409 | J79: Postman; REST Assured; PL/SQL | K79: Automated | L79: BUG-010 | M79: Not Run
A80: TC-FLOW-008 | B80: FLOW | C80: R-12 | D80: Cannot pay a cancelled order | E80: Integration | F80: API | G80: P2 | H80: Cancel, then pay | I80: 409 | J80: Postman; REST Assured | K80: Automated | M80: Not Run
A81: TC-FLOW-009 | B81: FLOW | C81: R-13 | D81: Cannot ship a cancelled order | E81: Integration | F81: API | G81: P2 | H81: Cancel, then ship | I81: 409 | J81: REST Assured | K81: Automated | M81: Not Run
A82: TC-FLOW-010 | B82: FLOW | C82: R-12 | D82: Cannot pay a shipped order | E82: Integration | F82: API | G82: P2 | H82: Ship, then pay | I82: 409 | J82: Postman | K82: Automated | M82: Not Run
A83: TC-FLOW-011 | B83: FLOW | C83: R-15 | D83: Cannot pay another user's order | E83: Security | F83: API | G83: P1 | H83: User B pays user A's order | I83: 403 | J83: Postman; REST Assured | K83: Automated | L83: BUG-003 | M83: Not Run
A84: TC-FLOW-012 | B84: FLOW | C84: R-15 | D84: Cannot ship or cancel another user's order | E84: Security | F84: API | G84: P1 | H84: User B ships / cancels user A's order | I84: 403 | J84: Manual | K84: Manual | L84: BUG-003 | M84: Not Run
A85: TC-FLOW-013 | B85: FLOW | C85: R-12 | D85: UI: pay and ship an order | E85: Integration | F85: UI | G85: P1 | H85: Open an order; press Pay, then Ship | I85: Status badge: paid, then shipped; Ship/Cancel disappear | J85: Cypress; Playwright | K85: Automated | M85: Not Run
A86: TC-FLOW-014 | B86: FLOW | C86: R-14 | D86: UI: cancel removes the actions | E86: Functional | F86: UI | G86: P2 | H86: Open an order; Cancel | I86: Status cancelled; Pay is gone | J86: Cypress | K86: Automated | M86: Not Run
A87: TC-FLOW-015 | B87: FLOW | C87: R-12 | D87: UI: action error is displayed | E87: Functional | F87: UI | G87: P3 | H87: Pay an order in another tab, then pay again here | I87: A role=alert error is shown | J87: Manual | K87: Manual | M87: Not Run
A88: TC-STAT-001 | B88: STAT | C88: R-16 | D88: New user has all-zero stats | E88: API | F88: API | G88: P2 | H88: GET /orders/stats for a new user | I88: All counts 0; revenue 0 | J88: REST Assured | K88: Automated | M88: Not Run
A89: TC-STAT-002 | B89: STAT | C89: R-16 | D89: Counts per status | E89: API | F89: API | G89: P2 | H89: Create orders in each state; GET stats | I89: by_status matches | J89: Postman; REST Assured | K89: Automated | M89: Not Run
A90: TC-STAT-003 | B90: STAT | C90: R-16 | D90: Revenue counts paid and shipped orders only | E90: API | F90: API | G90: P1 | H90: Mixed orders | I90: revenue = paid + shipped totals | J90: Postman; REST Assured | K90: Automated | M90: Not Run
A91: TC-STAT-004 | B91: STAT | C91: R-16 | D91: Stats require authentication | E91: Security | F91: API | G91: P2 | H91: GET stats without token | I91: 401 | J91: Postman; REST Assured | K91: Automated | M91: Not Run
A92: TC-STAT-005 | B92: STAT | C92: R-16 | D92: Stats are per user | E92: Security | F92: API | G92: P2 | H92: User B GETs stats | I92: User A's orders are not counted | J92: REST Assured | K92: Automated | M92: Not Run
A93: TC-A11Y-001 | B93: A11Y | C93: R-18 | D93: axe scan: login page | E93: Accessibility | F93: UI | G93: P2 | H93: Run cypress-axe (WCAG 2.1 A/AA) on / | I93: No violations | J93: Cypress | K93: Automated | L93: BUG-011 | M93: Not Run
A94: TC-A11Y-002 | B94: A11Y | C94: R-18 | D94: axe scan: orders list | E94: Accessibility | F94: UI | G94: P2 | H94: Run axe on the orders list | I94: No violations | J94: Cypress; Playwright | K94: Automated | L94: BUG-012 | M94: Not Run
A95: TC-A11Y-003 | B95: A11Y | C95: R-18 | D95: axe scan: new order form | E95: Accessibility | F95: UI | G95: P3 | H95: Run axe on the form | I95: No violations | J95: Cypress | K95: Automated | M95: Not Run
A96: TC-A11Y-004 | B96: A11Y | C96: R-18 | D96: Keyboard: Pay is operable | E96: Accessibility | F96: UI | G96: P1 | H96: Tab to Pay; press Enter | I96: Pay is a focusable button and activates | J96: Cypress | K96: Automated | L96: BUG-014 | M96: Not Run
A97: TC-A11Y-005 | B97: A11Y | C97: R-18 | D97: Keyboard-only end-to-end flow | E97: Accessibility | F97: UI | G97: P2 | H97: Complete register > order > pay with the keyboard only | I97: Every control reachable, visible focus, logical order | J97: Manual | K97: Manual | L97: BUG-014 | M97: Not Run
A98: TC-A11Y-006 | B98: A11Y | C98: R-18 | D98: Screen reader announces errors | E98: Accessibility | F98: UI | G98: P2 | H98: With NVDA/VoiceOver submit invalid forms | I98: Errors announced via role=alert | J98: Manual | K98: Manual | L98: BUG-015 | M98: Not Run
A99: TC-A11Y-007 | B99: A11Y | C99: R-18 | D99: Fields have accessible names | E99: Accessibility | F99: UI | G99: P2 | H99: Inspect inputs with a screen reader | I99: Each input has a label | J99: Cypress; Manual | K99: Partial | L99: BUG-011 | M99: Not Run
A100: TC-A11Y-008 | B100: A11Y | C100: R-18 | D100: Colour contrast >= 4.5:1 | E100: Accessibility | F100: UI | G100: P3 | H100: Measure text/background pairs | I100: All pass AA | J100: Cypress; Manual | K100: Partial | L100: BUG-012 | M100: Not Run
...

Sheet Requirements
A1: Req ID | B1: Requirement | C1: Test cases | D1: Covered? | E1: Automated or partial
A2: R-01 | B2: User registration | C2: =COUNTIF('Test Cases'!$C$2:$C$1000,A2) -> 6 | D2: =IF(C2>0,"Yes","No") -> Yes | E2: =COUNTIFS('Test Cases'!$C$2:$C$1000,A2,'Test Cases'!$K$2:$K$1000,"<>Manual") -> 5
A3: R-02 | B3: Password and profile field rules | C3: =COUNTIF('Test Cases'!$C$2:$C$1000,A3) -> 4 | D3: =IF(C3>0,"Yes","No") -> Yes | E3: =COUNTIFS('Test Cases'!$C$2:$C$1000,A3,'Test Cases'!$K$2:$K$1000,"<>Manual") -> 2
A4: R-03 | B4: Login | C4: =COUNTIF('Test Cases'!$C$2:$C$1000,A4) -> 6 | D4: =IF(C4>0,"Yes","No") -> Yes | E4: =COUNTIFS('Test Cases'!$C$2:$C$1000,A4,'Test Cases'!$K$2:$K$1000,"<>Manual") -> 6
A5: R-04 | B5: Token authentication and logout | C5: =COUNTIF('Test Cases'!$C$2:$C$1000,A5) -> 8 | D5: =IF(C5>0,"Yes","No") -> Yes | E5: =COUNTIFS('Test Cases'!$C$2:$C$1000,A5,'Test Cases'!$K$2:$K$1000,"<>Manual") -> 6
A6: R-05 | B6: Create order | C6: =COUNTIF('Test Cases'!$C$2:$C$1000,A6) -> 6 | D6: =IF(C6>0,"Yes","No") -> Yes | E6: =COUNTIFS('Test Cases'!$C$2:$C$1000,A6,'Test Cases'!$K$2:$K$1000,"<>Manual") -> 4
A7: R-06 | B7: Order input validation | C7: =COUNTIF('Test Cases'!$C$2:$C$1000,A7) -> 16 | D7: =IF(C7>0,"Yes","No") -> Yes | E7: =COUNTIFS('Test Cases'!$C$2:$C$1000,A7,'Test Cases'!$K$2:$K$1000,"<>Manual") -> 13
A8: R-07 | B8: Order totals | C8: =COUNTIF('Test Cases'!$C$2:$C$1000,A8) -> 3 | D8: =IF(C8>0,"Yes","No") -> Yes | E8: =COUNTIFS('Test Cases'!$C$2:$C$1000,A8,'Test Cases'!$K$2:$K$1000,"<>Manual") -> 2
A9: R-08 | B9: View order | C9: =COUNTIF('Test Cases'!$C$2:$C$1000,A9) -> 3 | D9: =IF(C9>0,"Yes","No") -> Yes | E9: =COUNTIFS('Test Cases'!$C$2:$C$1000,A9,'Test Cases'!$K$2:$K$1000,"<>Manual") -> 3
A10: R-09 | B10: List orders and pagination | C10: =COUNTIF('Test Cases'!$C$2:$C$1000,A10) -> 10 | D10: =IF(C10>0,"Yes","No") -> Yes | E10: =COUNTIFS('Test Cases'!$C$2:$C$1000,A10,'Test Cases'!$K$2:$K$1000,"<>Manual") -> 6
A11: R-10 | B11: Edit order | C11: =COUNTIF('Test Cases'!$C$2:$C$1000,A11) -> 3 | D11: =IF(C11>0,"Yes","No") -> Yes | E11: =COUNTIFS('Test Cases'!$C$2:$C$1000,A11,'Test Cases'!$K$2:$K$1000,"<>Manual") -> 2
A12: R-11 | B12: Delete order | C12: =COUNTIF('Test Cases'!$C$2:$C$1000,A12) -> 4 | D12: =IF(C12>0,"Yes","No") -> Yes | E12: =COUNTIFS('Test Cases'!$C$2:$C$1000,A12,'Test Cases'!$K$2:$K$1000,"<>Manual") -> 3
A13: R-12 | B13: Pay order | C13: =COUNTIF('Test Cases'!$C$2:$C$1000,A13) -> 7 | D13: =IF(C13>0,"Yes","No") -> Yes | E13: =COUNTIFS('Test Cases'!$C$2:$C$1000,A13,'Test Cases'!$K$2:$K$1000,"<>Manual") -> 6
... A21: R-20 | B21: Stored data integrity | C21: =COUNTIF('Test Cases'!$C$2:$C$1000,A21) -> 8 | D21: =IF(C21>0,"Yes","No") -> Yes | E21: =COUNTIFS('Test Cases'!$C$2:$C$1000,A21,'Test Cases'!$K$2:$K$1000,"<>Manual") -> 8

Sheet Seeded Bugs
A1: Bug | B1: Summary | C1: Layer | D1: Severity | E1: Linked test cases | F1: Detected by
A2: BUG-001 | B2: Registration accepts malformed e-mail addresses | C2: API | D2: Major | E2: =COUNTIF('Test Cases'!$L$2:$L$1000,A2) -> 1 | F2: Postman: Register invalid email format; JUnit: AuthApiTest.registerRejectsInvalidEmail (5 cases); Cypress: auth.cy.ts invalid e-mail
A3: BUG-002 | B3: Order quantity not range-checked (0, negative and >1000 accepted) | C3: API / DB | D3: Critical | E3: =COUNTIF('Test Cases'!$L$2:$L$1000,A3) -> 5 | F3: Postman: Quantity 0 / -5 / 1001; JUnit: OrderApiTest.invalidQuantity; Cypress: orders.cy.ts quantity 0; PL/SQL: QTY_POSITIVE
A4: BUG-003 | B4: Broken object-level authorization: any user can access any order (IDOR) | C4: API | D4: Blocker | E4: =COUNTIF('Test Cases'!$L$2:$L$1000,A4) -> 5 | F4: Postman: User B cannot read/update/pay user A order; JUnit: OrderApiTest.isolationBetweenUsers
A5: BUG-004 | B5: Order can be paid more than once (double charge) | C5: API / DB | D5: Blocker | E5: =COUNTIF('Test Cases'!$L$2:$L$1000,A5) -> 2 | F5: Postman: Pay again; JUnit: WorkflowApiTest.cannotPayTwice; PL/SQL: SINGLE_PAYMENT
A6: BUG-005 | B6: Unpaid order can be shipped | C6: API / DB | D6: Blocker | E6: =COUNTIF('Test Cases'!$L$2:$L$1000,A6) -> 2 | F6: Postman: Ship before pay; JUnit: WorkflowApiTest.cannotShipUnpaid; PL/SQL: SHIPPED_WAS_PAID
A7: BUG-006 | B7: Pagination repeats the last row of the previous page | C7: API / UI | D7: Major | E7: =COUNTIF('Test Cases'!$L$2:$L$1000,A7) -> 2 | F7: Postman: Pagination page 2 overlap; JUnit: OrderApiTest.paginationHasNoOverlap; Cypress: orders.cy.ts pagination
A8: BUG-007 | B8: Silent 10% discount on lines with quantity >= 10 | C8: API / DB | D8: Critical | E8: =COUNTIF('Test Cases'!$L$2:$L$1000,A8) -> 2 | F8: Postman: Bulk order no hidden discount; JUnit: OrderApiTest.noHiddenDiscount; Cypress: bulk total; PL/SQL: TOTAL_MATCHES_ITEMS
A9: BUG-008 | B9: Login reveals whether an e-mail is registered (user enumeration) | C9: API | D9: Major | E9: =COUNTIF('Test Cases'!$L$2:$L$1000,A9) -> 1 | F9: Postman: Login unknown email; JUnit: AuthApiTest.loginDoesNotEnumerateUsers; Cypress: auth.cy.ts same message
A10: BUG-009 | B10: customer_name longer than 100 chars causes HTTP 500 | C10: API | D10: Major | E10: =COUNTIF('Test Cases'!$L$2:$L$1000,A10) -> 1 | F10: Postman: customer_name 101 chars; JUnit: OrderApiTest.customerNameLength; Cypress: 101-char name
A11: BUG-010 | B11: Shipped orders can be cancelled | C11: API / DB | D11: Critical | E11: =COUNTIF('Test Cases'!$L$2:$L$1000,A11) -> 2 | F11: Postman: Cancel shipped order; JUnit: WorkflowApiTest.cannotCancelShipped; PL/SQL: CANCELLED_NOT_SHIPPED
A12: BUG-011 | B12: Login / register inputs have no accessible labels | C12: UI | D12: Major | E12: =COUNTIF('Test Cases'!$L$2:$L$1000,A12) -> 2 | F12: Cypress: accessibility.cy.ts login page
A13: BUG-012 | B13: Status badge text fails colour-contrast requirement | C13: UI | D13: Minor | E13: =COUNTIF('Test Cases'!$L$2:$L$1000,A13) -> 2 | F13: Cypress: accessibility.cy.ts orders list; Playwright: axe scan on mobile
... A16: BUG-015 | B16: Failed login shows no feedback | C16: UI | D16: Major | E16: =COUNTIF('Test Cases'!$L$2:$L$1000,A16) -> 2 | F16: Cypress: auth.cy.ts wrong credentials; Playwright: login error on mobile
